cicerone/settings.py
cicerone/parse/__init__.py
cicerone/parse/parser.py
cicerone/references/__init__.py
cicerone/references/reference.py
cicerone/references/reference_resolver.py
cicerone/spec/__init__.py
cicerone/spec/callback.py
cicerone/spec/components.py
cicerone/spec/encoding.py
cicerone/spec/example.py
cicerone/spec/header.py
cicerone/spec/info.py
cicerone/spec/link.py
cicerone/spec/media_type.py
cicerone/spec/model_utils.py
cicerone/spec/oauth_flows.py
cicerone/spec/openapi_spec.py
cicerone/spec/operation.py
cicerone/spec/parameter.py
cicerone/spec/path_item.py
cicerone/spec/paths.py
cicerone/spec/request_body.py
cicerone/spec/response.py
cicerone/spec/schema.py
cicerone/spec/security_scheme.py
cicerone/spec/server.py
cicerone/spec/tag.py
cicerone/spec/version.py
cicerone/spec/webhooks.py
cicerone-0.3.0.dist-info/METADATA
cicerone-0.3.0.dist-info/WHEEL
cicerone-0.3.0.dist-info/licenses/LICENSE
cicerone-0.3.0.dist-info/RECORD
