Metadata-Version: 2.4
Name: cicerone
Version: 0.3.0
Summary: Turn OpenAPI schemas into Pydantic models
Project-URL: Homepage, https://phalt.github.io/cicerone/
Project-URL: Changelog, https://phalt.github.io/cicerone/CHANGELOG/
Project-URL: Documentation, https://phalt.github.io/cicerone/
Project-URL: Issues, https://github.com/phalt/cicerone/issues
Author-email: Paul Hallett <paulandrewhallett@gmail.com>
License: MIT
License-File: LICENSE
Requires-Python: >=3.10
Requires-Dist: pydantic>=2.9
Requires-Dist: pyyaml>=6.0.1
